feat/__init__.py
feat/models/__init__.py
feat/models/configuration.py
feat/resources/floppy-disk-solid.svg
feat/resources/folder-open-regular.svg
feat/resources/FT-logo128.jpg
feat/resources/plus-solid.svg
feat/views/__init__.py
feat/views/gui.py
feat/views/gui_feat.ui
feat/views/gui_feat_new_file.ui
feat_feedback_tool-1.0.0.dist-info/entry_points.txt
feat_feedback_tool-1.0.0.dist-info/METADATA
feat_feedback_tool-1.0.0.dist-info/WHEEL
feat_feedback_tool-1.0.0.dist-info/RECORD
