Metadata-Version: 2.1
Name: feat-feedback-tool
Version: 1.0.0
Summary: Create fast feedback based on prewritten sentences combined with personalised messages.
Home-page: https://github.com/AnneliesVlaar/Feat
License: CC-BY-NC-SA-2.5
Author: AnneliesVlaar
Author-email: 66774020+AnneliesVlaar@users.noreply.github.com
Requires-Python: >=3.10,<3.13
Classifier: License :: Other/Proprietary License
Classifier: Programming Language :: Python :: 3
Classifier: Programming Language :: Python :: 3.10
Classifier: Programming Language :: Python :: 3.11
Classifier: Programming Language :: Python :: 3.12
Requires-Dist: pyqt6 (>=6.5.2,<7.0.0)
Requires-Dist: pyqtgraph (>=0.12.3,<0.13.0)
Requires-Dist: toml (>=0.10.2,<0.11.0)
Project-URL: Repository, https://github.com/AnneliesVlaar/Feat
